console_engine/__init__.py
console_engine/errors.py
console_engine/interpreter.py
console_engine/lexer.py
console_engine/parser.py
console_engine/shell.py
console_engine-0.1.3.dist-info/LICENSE.txt
console_engine-0.1.3.dist-info/METADATA
console_engine-0.1.3.dist-info/WHEEL
console_engine-0.1.3.dist-info/top_level.txt
console_engine-0.1.3.dist-info/RECORD
