Metadata-Version: 2.1
Name: console-engine
Version: 0.1.3
Summary: Custom, easy to integrate shell
Home-page: https://github.com/LightningV1p3r/console-engine
Author: LightningV1p3r
Author-email: LightningV1p3r@protonmail.com
License: LICENSE.txt
Platform: UNKNOWN
License-File: LICENSE.txt
Requires-Dist: colorama (==0.4.4)
Requires-Dist: viperlogger (==0.1.1)
